podflow/__init__.py
podflow/download_and_build.py
podflow/ffmpeg_judge.py
podflow/main.py
podflow/main_podcast.py
podflow/main_upload.py
podflow/parse_arguments.py
podflow/basic/__init__.py
podflow/basic/file_save.py
podflow/basic/folder_build.py
podflow/basic/get_duration.py
podflow/basic/get_file_list.py
podflow/basic/get_html_dict.py
podflow/basic/get_version_num.py
podflow/basic/http_client.py
podflow/basic/list_merge_tidy.py
podflow/basic/qr_code.py
podflow/basic/random_sequence.py
podflow/basic/split_dict.py
podflow/basic/time_format.py
podflow/basic/time_print.py
podflow/basic/time_stamp.py
podflow/basic/vary_replace.py
podflow/basic/write_log.py
podflow/bilibili/__init__.py
podflow/bilibili/build.py
podflow/bilibili/get.py
podflow/bilibili/login.py
podflow/config/__init__.py
podflow/config/build_original.py
podflow/config/channge_icon.py
podflow/config/correct_channelid.py
podflow/config/correct_config.py
podflow/config/get_channelid.py
podflow/config/get_channelid_id.py
podflow/config/get_config.py
podflow/download/__init__.py
podflow/download/convert_bytes.py
podflow/download/delete_part.py
podflow/download/dl_aideo_video.py
podflow/download/show_progress.py
podflow/download/wait_animation.py
podflow/download/youtube_and_bilibili_download.py
podflow/httpfs/__init__.py
podflow/httpfs/app_bottle.py
podflow/httpfs/browser.py
podflow/httpfs/download_bar.py
podflow/httpfs/get_channelid.py
podflow/httpfs/port_judge.py
podflow/httpfs/progress_bar.py
podflow/httpfs/to_html.py
podflow/makeup/__init__.py
podflow/makeup/del_makeup_format_fail.py
podflow/makeup/make_up_file.py
podflow/makeup/make_up_file_format_mod.py
podflow/makeup/make_up_file_mod.py
podflow/message/__init__.py
podflow/message/backup_zip_save.py
podflow/message/create_main_rss.py
podflow/message/display_qrcode_and_url.py
podflow/message/fail_message_initialize.py
podflow/message/format_time.py
podflow/message/get_media_name.py
podflow/message/get_original_rss.py
podflow/message/get_video_format.py
podflow-20260106.dist-info/METADATA
podflow-20260106.dist-info/WHEEL
podflow-20260106.dist-info/entry_points.txt
podflow-20260106.dist-info/top_level.txt
podflow-20260106.dist-info/RECORD
