Metadata-Version: 2.1
Name: podflow
Version: 20260106
Summary: A podcast server that includes YouTube and BiliBili
Author-email: gruel_zxz <zhuxizhouzxz@gmail.com>
License: MIT
Project-URL: Homepage, https://github.com/gruel-zxz/podflow
Requires-Python: >=3.8
Requires-Dist: astral>=3.2
Requires-Dist: bottle>=0.13.2
Requires-Dist: yt-dlp>=2025.8.20
Requires-Dist: chardet>=5.2.0
Requires-Dist: cherrypy>=18.10.0
Requires-Dist: pyqrcode>=1.2.1
Requires-Dist: requests>=2.32.3
Requires-Dist: ffmpeg-python>=0.2.0
Requires-Dist: BeautifulSoup4>=4.13.3
Requires-Dist: yt-dlp-apple-webkit-jsi; platform_system == "Darwin"
